toxy_bot/__init__.py
toxy_bot/api/__init__.py
toxy_bot/bot/__init__.py
toxy_bot/bot/app.py
toxy_bot/ml/__init__.py
toxy_bot/ml/client.py
toxy_bot/ml/config.py
toxy_bot/ml/datamodule.py
toxy_bot/ml/make_balanced_dataset.py
toxy_bot/ml/module.py
toxy_bot/ml/server.py
toxy_bot/ml/trainer.py
toxy_bot/ml/utils.py
toxy_bot/utils/-
toxy_bot/utils/__init__.py
toxy_bot/utils/config.py
toxy_bot-0.9.0.dist-info/METADATA
toxy_bot-0.9.0.dist-info/WHEEL
toxy_bot-0.9.0.dist-info/entry_points.txt
toxy_bot-0.9.0.dist-info/licenses/LICENSE
toxy_bot-0.9.0.dist-info/RECORD
