Metadata-Version: 2.4
Name: toxy-bot
Version: 0.9.0
Summary: A trained Discord Bot to detect and handle toxic messages in text channels.
Author-email: anitamaxvim <107803921+anitamaxvim@users.noreply.github.com>
License-Expression: MIT
License-File: LICENSE
Requires-Python: >=3.11
Requires-Dist: comet-ml>=3.49.7
Requires-Dist: datasets>=3.5.0
Requires-Dist: discord>=2.3.2
Requires-Dist: hf-xet>=1.0.3
Requires-Dist: jsonargparse>=4.38.0
Requires-Dist: lightning-sdk>=0.2.11
Requires-Dist: lightning[pytorch-extra]>=2.5.1
Requires-Dist: litserve>=0.2.7
Requires-Dist: matplotlib>=3.10.1
Requires-Dist: numpy==1.24; sys_platform == 'darwin'
Requires-Dist: pydantic>=2.11.2
Requires-Dist: seaborn>=0.12.1
Requires-Dist: torch==2.2.2; sys_platform == 'darwin'
Requires-Dist: torch>=2.6.0; sys_platform != 'darwin'
Requires-Dist: torchvision==0.17.2; sys_platform == 'darwin'
Requires-Dist: torchvision>=0.21.0; sys_platform != 'darwin'
Requires-Dist: transformers<4.51.0
